grpc_health/__init__.py
grpc_health/v1/__init__.py
grpc_health/v1/_async.py
grpc_health/v1/health.py
grpc_health/v1/health_pb2.py
grpc_health/v1/health_pb2.pyi
grpc_health/v1/health_pb2_grpc.py
grpcio_health_checking-1.76.0.dist-info/LICENSE
grpcio_health_checking-1.76.0.dist-info/METADATA
grpcio_health_checking-1.76.0.dist-info/WHEEL
grpcio_health_checking-1.76.0.dist-info/top_level.txt
grpcio_health_checking-1.76.0.dist-info/RECORD
